AtomPacker/__init__.py
AtomPacker/core/__init__.py
AtomPacker/core/grid/__init__.py
AtomPacker/core/grid/characterize.py
AtomPacker/core/grid/coordinates.py
AtomPacker/core/io/__init__.py
AtomPacker/core/io/mmcif/__init__.py
AtomPacker/core/io/mmcif/file.py
AtomPacker/core/io/mol2/__init__.py
AtomPacker/core/io/mol2/file.py
AtomPacker/core/io/pdb/__init__.py
AtomPacker/core/io/pdb/file.py
AtomPacker/core/io/vdw/__init__.py
AtomPacker/core/io/vdw/file.py
AtomPacker/core/io/xyz/__init__.py
AtomPacker/core/io/xyz/file.py
AtomPacker/structure/Cage.py
AtomPacker/structure/Cavity.py
AtomPacker/structure/Cluster.py
AtomPacker/structure/Openings.py
AtomPacker/structure/__init__.py
AtomPacker/structure/data.py
atompacker-0.5.1.dist-info/licenses/LICENSE
atompacker-0.5.1.dist-info/METADATA
atompacker-0.5.1.dist-info/WHEEL
atompacker-0.5.1.dist-info/top_level.txt
atompacker-0.5.1.dist-info/RECORD
