Metadata-Version: 2.4
Name: AtomPacker
Version: 0.5.1
Summary: A python package for packing nanoclusters into supramolecular cages
Author: Gabriel E. Jara, Paulo S. Lopes-de-Oliveira, György Szalóki
Author-email: "João V. S. Guerra" <jvsguerra@gmail.com>
Maintainer-email: "João V. S. Guerra" <jvsguerra@gmail.com>
License:                     GNU GENERAL PUBLIC LICENSE
Project-URL: homepage, https://github.com/cnpem/AtomPacker
Project-URL: documentation, https://cnpem.github.io/AtomPacker/
Project-URL: issues, https://github.com/cnpem/AtomPacker/issues
Keywords: computational chemistry,atom packing,sphere packing
Classifier: Development Status :: 4 - Beta
Classifier: Intended Audience :: Science/Research
Classifier: License :: OSI Approved :: GNU General Public License v3 (GPLv3)
Classifier: Programming Language :: Python
Classifier: Programming Language :: Python :: 3
Classifier: Programming Language :: Python :: 3.10
Classifier: Programming Language :: Python :: 3.11
Classifier: Programming Language :: Python :: 3.12
Classifier: Programming Language :: Python :: 3.13
Classifier: Programming Language :: Python :: 3 :: Only
Classifier: Operating System :: Microsoft :: Windows
Classifier: Operating System :: Unix
Classifier: Operating System :: MacOS
Classifier: Topic :: Scientific/Engineering :: Chemistry
Classifier: Topic :: Scientific/Engineering :: Physics
Requires-Python: >=3.10
License-File: LICENSE
Requires-Dist: ase>=3.26.0
Requires-Dist: biopython>=1.85.0
Requires-Dist: MDAnalysis>=2.9.0
Requires-Dist: numpy>=2.2.0
Requires-Dist: pandas>=2.3.0
Requires-Dist: plotly>=6.0.0
Requires-Dist: pyKVFinder>=0.8.0
Requires-Dist: scikit-learn>=1.7.0
Requires-Dist: tqdm>=4.67.0
Provides-Extra: dev
Requires-Dist: black==25.1.0; extra == "dev"
Requires-Dist: flake8==7.3.0; extra == "dev"
Requires-Dist: pytest==8.4.2; extra == "dev"
Provides-Extra: docs
Requires-Dist: sphinx>=8.1.3; extra == "docs"
Requires-Dist: sphinx-rtd-theme>=3.0.2; extra == "docs"
Dynamic: license-file
